README.rst
setup.cfg
setup.py
pyIG/__init__.py
pyIG/config.py
pyIG/lightstreamer.py
pyIG/rest.py
pyIG/stream.py
pyIG/utils.py
pyIG.egg-info/PKG-INFO
pyIG.egg-info/SOURCES.txt
pyIG.egg-info/dependency_links.txt
pyIG.egg-info/requires.txt
pyIG.egg-info/top_level.txt