Metadata-Version: 1.1
Name: pyIG
Version: 1.0.0
Summary: IG Markets Trading API
Home-page: https://github.com/th3sys/pyIG
Author: Alexy Shelest
Author-email: alexy@th3sys.com
License: MIT
Keywords: IG Markets API trading-api trading
Platform: any
Classifier: Programming Language :: Python :: 3.6
